client_chat_adub/__init__.py
client_chat_adub/client.py
client_chat_adub/client/__init__.py
client_chat_adub/client/add_contact.py
client_chat_adub/client/client_db.py
client_chat_adub/client/del_contact.py
client_chat_adub/client/main_window.py
client_chat_adub/client/main_window_conv.py
client_chat_adub/client/start_dialog.py
client_chat_adub/client/transport.py
client_chat_adub/common/__init__.py
client_chat_adub/common/data_transfer.py
client_chat_adub/common/decorators.py
client_chat_adub/common/descriptors.py
client_chat_adub/common/errors.py
client_chat_adub/common/metaclasses.py
client_chat_adub/logs/__init__.py
client_chat_adub/logs/client_log_config.py
client_chat_adub/logs/server_log_config.py
client_chat_project_adub-0.1.dist-info/METADATA
client_chat_project_adub-0.1.dist-info/WHEEL
client_chat_project_adub-0.1.dist-info/top_level.txt
client_chat_project_adub-0.1.dist-info/RECORD
